aneel/__init__.py
aneel-0.0.7.dist-info/DESCRIPTION.rst
aneel-0.0.7.dist-info/METADATA
aneel-0.0.7.dist-info/RECORD
aneel-0.0.7.dist-info/WHEEL
aneel-0.0.7.dist-info/metadata.json
aneel-0.0.7.dist-info/top_level.txt
