Metadata-Version: 2.0
Name: aneel
Version: 0.0.7
Summary: This package performs various calculations related to ANEEL regulations.
Home-page: https://github.com/renatoefsousa/ANEEL
Author: Renato Eduardo Farias de Sousa
Author-email: renato.ef.sousa@gmail.com
License: MIT License
Keywords: aneel calculations regulations
Platform: UNKNOWN
Requires-Dist: csv
Requires-Dist: datetime
Requires-Dist: json
